requestgen/__init__.py
edgerun_request_generator-1.0.0.dist-info/LICENSE
edgerun_request_generator-1.0.0.dist-info/METADATA
edgerun_request_generator-1.0.0.dist-info/WHEEL
edgerun_request_generator-1.0.0.dist-info/top_level.txt
edgerun_request_generator-1.0.0.dist-info/RECORD
