Metadata-Version: 2.1
Name: edgerun-request-generator
Version: 1.0.0
Summary: Edge Run Request Generator
Home-page: https://github.com/edgerun/request-generator
Author: Thomas Rausch, Philipp Raith
Author-email: t.rausch@dsg.tuwien.ac.at, p.raith@dsg.tuwien.ac.at
License: UNKNOWN
Platform: UNKNOWN
Classifier: Programming Language :: Python :: 3
Classifier: Operating System :: OS Independent
License-File: LICENSE
Requires-Dist: simpy (>=3.0.11)
Requires-Dist: pandas (>=1.4.3)
